sdp_transform/__init__.py
sdp_transform/__version__.py
sdp_transform/grammar.py
sdp_transform/parser.py
sdp_transform/writer.py
sdp_transform-1.0.6.dist-info/LICENSE
sdp_transform-1.0.6.dist-info/METADATA
sdp_transform-1.0.6.dist-info/WHEEL
sdp_transform-1.0.6.dist-info/RECORD
