Metadata-Version: 2.1
Name: sdp-transform
Version: 1.0.6
Summary: A simple Python parser and writer of SDP.
License: MIT
Author: Jiang Yue
Author-email: maze1024@gmail.com
Requires-Python: >=3.6.0
Classifier: License :: OSI Approved :: MIT License
Classifier: Programming Language :: Python :: 3
Classifier: Programming Language :: Python :: 3.6
Classifier: Programming Language :: Python :: 3.7
Classifier: Programming Language :: Python :: 3.8
Classifier: Programming Language :: Python :: 3.9
Classifier: Programming Language :: Python :: 3.10
Classifier: Programming Language :: Python :: 3.11
